redvty/__init__.py
redvty/redvty.py
redvty-0.0.1.dist-info/LICENSE
redvty-0.0.1.dist-info/METADATA
redvty-0.0.1.dist-info/WHEEL
redvty-0.0.1.dist-info/top_level.txt
redvty-0.0.1.dist-info/RECORD
